airflow_tecton/__init__.py
airflow_tecton/hooks/__init__.py
airflow_tecton/hooks/tecton_hook.py
airflow_tecton/operators/__init__.py
airflow_tecton/operators/df_utils.py
airflow_tecton/operators/job_utils.py
airflow_tecton/operators/tecton_feature_table_job_operator.py
airflow_tecton/operators/tecton_feature_table_trigger_operator.py
airflow_tecton/operators/tecton_job_operator.py
airflow_tecton/operators/tecton_trigger_operator.py
airflow_tecton/sensors/__init__.py
airflow_tecton/sensors/tecton_sensor.py
airflow_tecton-0.1.1.dist-info/LICENSE
airflow_tecton-0.1.1.dist-info/METADATA
airflow_tecton-0.1.1.dist-info/WHEEL
airflow_tecton-0.1.1.dist-info/entry_points.txt
airflow_tecton-0.1.1.dist-info/top_level.txt
airflow_tecton-0.1.1.dist-info/RECORD
