Metadata-Version: 2.1
Name: airflow-tecton
Version: 0.1.1
Summary: Provider for using Tecton with Airflow.
Home-page: http://tecton.ai/
License: Apache License 2.0
Classifier: Framework :: Apache Airflow
Classifier: Framework :: Apache Airflow :: Provider
Requires-Python: >=3.7
License-File: LICENSE
Requires-Dist: apache-airflow>=2.0
Requires-Dist: requests
Requires-Dist: pandas
Requires-Dist: pyarrow
Requires-Dist: fastparquet
